Metadata-Version: 2.1
Name: eze-example-plugin
Version: 0.8.0
Summary: Example plugin for helping eze-cli plugin makers
Home-page: https://github.com/RiverSafeUK/eze-example-plugin
Author: RiverSafe,
Author-email: anthony.mckale@riversafe.co.uk,
License: "MIT license"
Project-URL: Homepage, https://github.com/RiverSafeUK/eze-example-plugin
Project-URL: Source, https://github.com/RiverSafeUK/eze-example-plugin
Keywords: eze,eze-cli
Platform: UNKNOWN
Classifier: Development Status :: 3 - Alpha
Classifier: Intended Audience :: Developers
Classifier: License :: OSI Approved :: MIT License
Classifier: Topic :: Software Development :: Testing
Classifier: Topic :: Security
Classifier: Topic :: Utilities
Classifier: Operating System :: OS Independent
Classifier: Programming Language :: Python
Classifier: Programming Language :: Python :: 3.7
Classifier: Programming Language :: Python :: 3.8
Classifier: Programming Language :: Python :: 3.9
Requires-Python: >=3.7
License-File: LICENSE.md
